{
  "generator-jhipster": {
    "blueprints": [],
    "otherModules": [],
    "applicationType": "monolith",
    "baseName": "n1ceblog",
    "jhipsterVersion": "7.0.1",
    "skipClient": false,
    "skipServer": false,
    "skipUserManagement": false,
    "skipCheckLengthOfIdentifier": false,
    "skipFakeData": false,
    "jhiPrefix": "jhi",
    "entitySuffix": "",
    "dtoSuffix": "DTO",
    "testFrameworks": [],
    "pages": [],
    "creationTimestamp": 1631130366302,
    "serviceDiscoveryType": false,
    "reactive": false,
    "authenticationType": "jwt",
    "packageName": "community.n1ce.blog",
    "serverPort": "8080",
    "cacheProvider": "ehcache",
    "enableHibernateCache": false,
    "databaseType": "mongodb",
    "buildTool": "maven",
    "serverSideOptions": [],
    "websocket": false,
    "searchEngine": false,
    "messageBroker": false,
    "enableSwaggerCodegen": false,
    "clientFramework": "angularX",
    "withAdminUi": true,
    "clientTheme": "none",
    "enableTranslation": true,
    "nativeLanguage": "en",
    "packageFolder": "community/n1ce/blog",
    "jwtSecretKey": "YTBiZTBjMDRlYTRlMmExYTliYzkxMWVlNmQwZjFhY2VhMjBlN2U3YTgyYzFmYWNkMDY0MjEwZGM4ZDhmMTQ4MmU4NDNiZjc2YWNmNDgwODk5MmQyNDBlZWRlYzU5OGQ2OGNmNmY4MWNhOGQ5ODNmNDI2MzAxMTVlMjlkOTgwNTE=",
    "devDatabaseType": "mongodb",
    "prodDatabaseType": "mongodb",
    "clientPackageManager": "npm",
    "clientThemeVariant": "",
    "languages": ["en", "it"],
    "lastLiquibaseTimestamp": 1631144261000,
    "entities": ["BlogPost", "BlogCategory", "Expert", "ServiceCategory", "ExpertPlatformService", "ServiceReview"]
  }
}
